VideoPlayerWidget/__init__.py
VideoPlayerWidget/_frontend.py
VideoPlayerWidget/_version.py
VideoPlayerWidget/video.py
VideoPlayerWidget/labextension/videoplayerwidget-0.1.0.tgz
VideoPlayerWidget/nbextension/__init__.py
VideoPlayerWidget/nbextension/static/extension.js
VideoPlayerWidget/nbextension/static/index.js
VideoPlayerWidget/nbextension/static/index.js.map
VideoPlayerWidget/tests/__init__.py
VideoPlayerWidget/tests/conftest.py
VideoPlayerWidget/tests/test_nbextension_path.py
VideoPlayerWidget/tests/test_videoplayerwidget.py
VideoPlayerWidget-0.1.0.data/data/etc/jupyter/nbconfig/notebook.d/VideoPlayerWidget.json
VideoPlayerWidget-0.1.0.data/data/share/jupyter/lab/extensions/videoplayerwidget-0.1.0.tgz
VideoPlayerWidget-0.1.0.data/data/share/jupyter/nbextensions/VideoPlayerWidget/extension.js
VideoPlayerWidget-0.1.0.data/data/share/jupyter/nbextensions/VideoPlayerWidget/index.js
VideoPlayerWidget-0.1.0.data/data/share/jupyter/nbextensions/VideoPlayerWidget/index.js.map
VideoPlayerWidget-0.1.0.dist-info/LICENSE.txt
VideoPlayerWidget-0.1.0.dist-info/METADATA
VideoPlayerWidget-0.1.0.dist-info/WHEEL
VideoPlayerWidget-0.1.0.dist-info/top_level.txt
VideoPlayerWidget-0.1.0.dist-info/RECORD
